{
    "id": "star_aramizda-kalsin",
    "imdb_id": "star_aramizda-kalsin",
    "name": "Aramızda Kalsın",
    "original_name": "Aramızda Kalsın",
    "overview": "Star TV DIZI İçeriği",
    "poster": "https://media.startv.com.tr/star-tv/images/d1c3757240e4babba0cd5346.jpg",
    "backdrop": "https://media.startv.com.tr/star-tv/images/d1c3757240e4babba0cd5346.jpg",
    "year": "2026",
    "rating": 10.0,
    "genres": [
        "Yerli",
        "Dizi"
    ],
    "categories": [
        "Star TV",
        "Dizi",
        "Yerli"
    ],
    "cast": [],
    "episodes": [
        {
            "season": 1,
            "episode": 1,
            "name": "1. Bölüm",
            "overview": "",
            "still_path": "https://media.startv.com.tr/star-tv/images/6b30b74e415fa275b504f6d2.jpg",
            "vote_average": 0.0,
            "link": "https://dygvideo.dygdigital.com/api/redirect?PublisherId=1&ReferenceId=StarTV_44917&SecretKey=NtvApiSecret2014*&.m3u8"
        },
        {
            "season": 1,
            "episode": 2,
            "name": "2. Bölüm",
            "overview": "",
            "still_path": "https://media.startv.com.tr/star-tv/images/75aed90f4a8d97d4d70729ae.jpg",
            "vote_average": 0.0,
            "link": "https://dygvideo.dygdigital.com/api/redirect?PublisherId=1&ReferenceId=StarTV_45091&SecretKey=NtvApiSecret2014*&.m3u8"
        },
        {
            "season": 1,
            "episode": 3,
            "name": "3. Bölüm",
            "overview": "",
            "still_path": "https://media.startv.com.tr/star-tv/images/3e389e1f433c98b178804153.jpg",
            "vote_average": 0.0,
            "link": "https://dygvideo.dygdigital.com/api/redirect?PublisherId=1&ReferenceId=StarTV_45279&SecretKey=NtvApiSecret2014*&.m3u8"
        },
        {
            "season": 1,
            "episode": 4,
            "name": "4. Bölüm",
            "overview": "",
            "still_path": "https://media.startv.com.tr/star-tv/images/f81cc5db4db984fa137b7f9e.jpg",
            "vote_average": 0.0,
            "link": "https://dygvideo.dygdigital.com/api/redirect?PublisherId=1&ReferenceId=StarTV_45428&SecretKey=NtvApiSecret2014*&.m3u8"
        },
        {
            "season": 1,
            "episode": 5,
            "name": "5. Bölüm",
            "overview": "",
            "still_path": "https://media.startv.com.tr/star-tv/images/5d9e3cf640afb03ff8aa59d5.jpg",
            "vote_average": 0.0,
            "link": "https://dygvideo.dygdigital.com/api/redirect?PublisherId=1&ReferenceId=StarTV_45695&SecretKey=NtvApiSecret2014*&.m3u8"
        },
        {
            "season": 1,
            "episode": 6,
            "name": "6. Bölüm",
            "overview": "",
            "still_path": "https://media.startv.com.tr/star-tv/images/99696631476ca9f986f9247e.jpg",
            "vote_average": 0.0,
            "link": "https://dygvideo.dygdigital.com/api/redirect?PublisherId=1&ReferenceId=StarTV_45849&SecretKey=NtvApiSecret2014*&.m3u8"
        },
        {
            "season": 1,
            "episode": 7,
            "name": "7. Bölüm",
            "overview": "",
            "still_path": "https://media.startv.com.tr/star-tv/images/505f6c1b420895afce15cc0c.jpg",
            "vote_average": 0.0,
            "link": "https://dygvideo.dygdigital.com/api/redirect?PublisherId=1&ReferenceId=StarTV_46069&SecretKey=NtvApiSecret2014*&.m3u8"
        },
        {
            "season": 1,
            "episode": 8,
            "name": "8. Bölüm",
            "overview": "",
            "still_path": "https://media.startv.com.tr/star-tv/images/bbfec0b042ba86b67f1a1890.jpg",
            "vote_average": 0.0,
            "link": "https://dygvideo.dygdigital.com/api/redirect?PublisherId=1&ReferenceId=StarTV_46258&SecretKey=NtvApiSecret2014*&.m3u8"
        },
        {
            "season": 1,
            "episode": 9,
            "name": "9. Bölüm",
            "overview": "",
            "still_path": "https://media.startv.com.tr/star-tv/images/ef09e9e0429d8956cef1bdf5.jpg",
            "vote_average": 0.0,
            "link": "https://dygvideo.dygdigital.com/api/redirect?PublisherId=1&ReferenceId=StarTV_46437&SecretKey=NtvApiSecret2014*&.m3u8"
        },
        {
            "season": 1,
            "episode": 10,
            "name": "10. Bölüm",
            "overview": "",
            "still_path": "https://media.startv.com.tr/star-tv/images/d53a4f1c4c209c6a77d4ff4e.jpg",
            "vote_average": 0.0,
            "link": "https://dygvideo.dygdigital.com/api/redirect?PublisherId=1&ReferenceId=StarTV_46629&SecretKey=NtvApiSecret2014*&.m3u8"
        },
        {
            "season": 1,
            "episode": 11,
            "name": "11. Bölüm",
            "overview": "",
            "still_path": "https://media.startv.com.tr/star-tv/images/a9e046684860bda05a55cebb.jpg",
            "vote_average": 0.0,
            "link": "https://dygvideo.dygdigital.com/api/redirect?PublisherId=1&ReferenceId=StarTV_46795&SecretKey=NtvApiSecret2014*&.m3u8"
        },
        {
            "season": 1,
            "episode": 12,
            "name": "12. Bölüm",
            "overview": "",
            "still_path": "https://media.startv.com.tr/star-tv/images/fc5d372f4b308efe6166f3ac.jpg",
            "vote_average": 0.0,
            "link": "https://dygvideo.dygdigital.com/api/redirect?PublisherId=1&ReferenceId=StarTV_46969&SecretKey=NtvApiSecret2014*&.m3u8"
        },
        {
            "season": 1,
            "episode": 13,
            "name": "13. Bölüm",
            "overview": "",
            "still_path": "https://media.startv.com.tr/star-tv/images/f0ac0f0443899d366b6f4656.jpg",
            "vote_average": 0.0,
            "link": "https://dygvideo.dygdigital.com/api/redirect?PublisherId=1&ReferenceId=StarTV_47148&SecretKey=NtvApiSecret2014*&.m3u8"
        },
        {
            "season": 1,
            "episode": 14,
            "name": "14. Bölüm",
            "overview": "",
            "still_path": "https://media.startv.com.tr/star-tv/images/dc58be55487f861a62563b8c.jpg",
            "vote_average": 0.0,
            "link": "https://dygvideo.dygdigital.com/api/redirect?PublisherId=1&ReferenceId=StarTV_47255&SecretKey=NtvApiSecret2014*&.m3u8"
        },
        {
            "season": 1,
            "episode": 15,
            "name": "15. Bölüm",
            "overview": "",
            "still_path": "https://media.startv.com.tr/star-tv/images/639e24fc410ba18d2038a34a.jpg",
            "vote_average": 0.0,
            "link": "https://dygvideo.dygdigital.com/api/redirect?PublisherId=1&ReferenceId=StarTV_47407&SecretKey=NtvApiSecret2014*&.m3u8"
        },
        {
            "season": 1,
            "episode": 16,
            "name": "16. Bölüm",
            "overview": "",
            "still_path": "https://media.startv.com.tr/star-tv/images/d0dcb02a42358034acad935f.jpg",
            "vote_average": 0.0,
            "link": "https://dygvideo.dygdigital.com/api/redirect?PublisherId=1&ReferenceId=StarTV_47642&SecretKey=NtvApiSecret2014*&.m3u8"
        },
        {
            "season": 1,
            "episode": 17,
            "name": "17. Bölüm",
            "overview": "",
            "still_path": "https://media.startv.com.tr/star-tv/images/727230f9493e8fe83ceb3c9d.jpg",
            "vote_average": 0.0,
            "link": "https://dygvideo.dygdigital.com/api/redirect?PublisherId=1&ReferenceId=StarTV_47765&SecretKey=NtvApiSecret2014*&.m3u8"
        },
        {
            "season": 1,
            "episode": 18,
            "name": "18. Bölüm",
            "overview": "",
            "still_path": "https://media.startv.com.tr/star-tv/images/d93ff42545d6bcf352b1bbad.jpg",
            "vote_average": 0.0,
            "link": "https://dygvideo.dygdigital.com/api/redirect?PublisherId=1&ReferenceId=StarTV_47863&SecretKey=NtvApiSecret2014*&.m3u8"
        },
        {
            "season": 1,
            "episode": 19,
            "name": "19. Bölüm",
            "overview": "",
            "still_path": "https://media.startv.com.tr/star-tv/images/e7bc9d004cb48486eeb6b1c0.jpg",
            "vote_average": 0.0,
            "link": "https://dygvideo.dygdigital.com/api/redirect?PublisherId=1&ReferenceId=StarTV_47956&SecretKey=NtvApiSecret2014*&.m3u8"
        },
        {
            "season": 1,
            "episode": 20,
            "name": "20. Bölüm",
            "overview": "",
            "still_path": "https://media.startv.com.tr/star-tv/images/94a37b9844f2a7f0c2d07386.jpg",
            "vote_average": 0.0,
            "link": "https://dygvideo.dygdigital.com/api/redirect?PublisherId=1&ReferenceId=StarTV_48089&SecretKey=NtvApiSecret2014*&.m3u8"
        },
        {
            "season": 1,
            "episode": 21,
            "name": "21. Bölüm",
            "overview": "",
            "still_path": "https://media.startv.com.tr/star-tv/images/fa27088f42499bd5efe882e8.jpg",
            "vote_average": 0.0,
            "link": "https://dygvideo.dygdigital.com/api/redirect?PublisherId=1&ReferenceId=StarTV_48328&SecretKey=NtvApiSecret2014*&.m3u8"
        },
        {
            "season": 1,
            "episode": 22,
            "name": "22. Bölüm",
            "overview": "",
            "still_path": "https://media.startv.com.tr/star-tv/images/1193cf7e484a9f10b94101da.jpg",
            "vote_average": 0.0,
            "link": "https://dygvideo.dygdigital.com/api/redirect?PublisherId=1&ReferenceId=StarTV_48535&SecretKey=NtvApiSecret2014*&.m3u8"
        },
        {
            "season": 1,
            "episode": 23,
            "name": "23. Bölüm",
            "overview": "",
            "still_path": "https://media.startv.com.tr/star-tv/images/8bcea0ac4e4c8c3383ee69f2.jpg",
            "vote_average": 0.0,
            "link": "https://dygvideo.dygdigital.com/api/redirect?PublisherId=1&ReferenceId=StarTV_48695&SecretKey=NtvApiSecret2014*&.m3u8"
        },
        {
            "season": 1,
            "episode": 24,
            "name": "24. Bölüm",
            "overview": "",
            "still_path": "https://media.startv.com.tr/star-tv/images/1dbbd0e84f9d836e6e0970d1.jpg",
            "vote_average": 0.0,
            "link": "https://dygvideo.dygdigital.com/api/redirect?PublisherId=1&ReferenceId=StarTV_48835&SecretKey=NtvApiSecret2014*&.m3u8"
        },
        {
            "season": 1,
            "episode": 25,
            "name": "25. Bölüm",
            "overview": "",
            "still_path": "https://media.startv.com.tr/star-tv/images/30a1d63b4a14a47b7d611678.jpg",
            "vote_average": 0.0,
            "link": "https://dygvideo.dygdigital.com/api/redirect?PublisherId=1&ReferenceId=StarTV_48993&SecretKey=NtvApiSecret2014*&.m3u8"
        },
        {
            "season": 1,
            "episode": 26,
            "name": "26. Bölüm",
            "overview": "",
            "still_path": "https://media.startv.com.tr/star-tv/images/5107909a42b8a614940118b4.jpg",
            "vote_average": 0.0,
            "link": "https://dygvideo.dygdigital.com/api/redirect?PublisherId=1&ReferenceId=StarTV_49132&SecretKey=NtvApiSecret2014*&.m3u8"
        },
        {
            "season": 1,
            "episode": 27,
            "name": "27. Bölüm",
            "overview": "",
            "still_path": "https://media.startv.com.tr/star-tv/images/87d2d06d4e458da97cfbc503.jpg",
            "vote_average": 0.0,
            "link": "https://dygvideo.dygdigital.com/api/redirect?PublisherId=1&ReferenceId=StarTV_49283&SecretKey=NtvApiSecret2014*&.m3u8"
        },
        {
            "season": 1,
            "episode": 28,
            "name": "28. Bölüm",
            "overview": "",
            "still_path": "https://media.startv.com.tr/star-tv/images/081402844889a76df01e6363.jpg",
            "vote_average": 0.0,
            "link": "https://dygvideo.dygdigital.com/api/redirect?PublisherId=1&ReferenceId=StarTV_49445&SecretKey=NtvApiSecret2014*&.m3u8"
        },
        {
            "season": 1,
            "episode": 29,
            "name": "29. Bölüm",
            "overview": "",
            "still_path": "https://media.startv.com.tr/star-tv/images/0822acb2410cbbd129f02649.jpg",
            "vote_average": 0.0,
            "link": "https://dygvideo.dygdigital.com/api/redirect?PublisherId=1&ReferenceId=StarTV_49605&SecretKey=NtvApiSecret2014*&.m3u8"
        },
        {
            "season": 1,
            "episode": 30,
            "name": "30. Bölüm",
            "overview": "",
            "still_path": "https://media.startv.com.tr/star-tv/images/a32391fa470bb433620702b3.jpg",
            "vote_average": 0.0,
            "link": "https://dygvideo.dygdigital.com/api/redirect?PublisherId=1&ReferenceId=StarTV_49739&SecretKey=NtvApiSecret2014*&.m3u8"
        },
        {
            "season": 1,
            "episode": 31,
            "name": "31. Bölüm",
            "overview": "",
            "still_path": "https://media.startv.com.tr/star-tv/images/ea19d1464f4f9af0bd49a0ba.jpg",
            "vote_average": 0.0,
            "link": "https://dygvideo.dygdigital.com/api/redirect?PublisherId=1&ReferenceId=StarTV_49937&SecretKey=NtvApiSecret2014*&.m3u8"
        },
        {
            "season": 1,
            "episode": 32,
            "name": "32. Bölüm",
            "overview": "",
            "still_path": "https://media.startv.com.tr/star-tv/images/292eb9eb463591c55b83fb49.jpg",
            "vote_average": 0.0,
            "link": "https://dygvideo.dygdigital.com/api/redirect?PublisherId=1&ReferenceId=StarTV_50149&SecretKey=NtvApiSecret2014*&.m3u8"
        },
        {
            "season": 1,
            "episode": 33,
            "name": "33. Bölüm",
            "overview": "",
            "still_path": "https://media.startv.com.tr/star-tv/images/a416a89b42a9a4300c0afd3c.jpg",
            "vote_average": 0.0,
            "link": "https://dygvideo.dygdigital.com/api/redirect?PublisherId=1&ReferenceId=StarTV_50303&SecretKey=NtvApiSecret2014*&.m3u8"
        },
        {
            "season": 1,
            "episode": 34,
            "name": "34. Bölüm",
            "overview": "",
            "still_path": "https://media.startv.com.tr/star-tv/images/781b0fdb44ba856123b1f03c.jpg",
            "vote_average": 0.0,
            "link": "https://dygvideo.dygdigital.com/api/redirect?PublisherId=1&ReferenceId=StarTV_50422&SecretKey=NtvApiSecret2014*&.m3u8"
        },
        {
            "season": 1,
            "episode": 35,
            "name": "35. Bölüm",
            "overview": "",
            "still_path": "https://media.startv.com.tr/star-tv/images/b27b420d4c1fb7eaea3b6d42.jpg",
            "vote_average": 0.0,
            "link": "https://dygvideo.dygdigital.com/api/redirect?PublisherId=1&ReferenceId=StarTV_50516&SecretKey=NtvApiSecret2014*&.m3u8"
        },
        {
            "season": 1,
            "episode": 36,
            "name": "36. Bölüm",
            "overview": "",
            "still_path": "https://media.startv.com.tr/star-tv/images/5a90a27148bbbbf1fdf0e7fa.jpg",
            "vote_average": 0.0,
            "link": "https://dygvideo.dygdigital.com/api/redirect?PublisherId=1&ReferenceId=StarTV_51420&SecretKey=NtvApiSecret2014*&.m3u8"
        },
        {
            "season": 1,
            "episode": 37,
            "name": "37. Bölüm",
            "overview": "",
            "still_path": "https://media.startv.com.tr/star-tv/images/37b646214ee7b0539bc8c7bf.jpg",
            "vote_average": 0.0,
            "link": "https://dygvideo.dygdigital.com/api/redirect?PublisherId=1&ReferenceId=StarTV_51525&SecretKey=NtvApiSecret2014*&.m3u8"
        },
        {
            "season": 1,
            "episode": 38,
            "name": "38. Bölüm",
            "overview": "",
            "still_path": "https://media.startv.com.tr/star-tv/images/ea81a1e24d5f85b87684528d.jpg",
            "vote_average": 0.0,
            "link": "https://dygvideo.dygdigital.com/api/redirect?PublisherId=1&ReferenceId=StarTV_51675&SecretKey=NtvApiSecret2014*&.m3u8"
        },
        {
            "season": 1,
            "episode": 39,
            "name": "39. Bölüm",
            "overview": "",
            "still_path": "https://media.startv.com.tr/star-tv/images/630a686c4d789b927a1dd4e1.jpg",
            "vote_average": 0.0,
            "link": "https://dygvideo.dygdigital.com/api/redirect?PublisherId=1&ReferenceId=StarTV_51775&SecretKey=NtvApiSecret2014*&.m3u8"
        },
        {
            "season": 1,
            "episode": 40,
            "name": "40. Bölüm",
            "overview": "",
            "still_path": "https://media.startv.com.tr/star-tv/images/0f9fcdf74c94996b0617b2cc.jpg",
            "vote_average": 0.0,
            "link": "https://dygvideo.dygdigital.com/api/redirect?PublisherId=1&ReferenceId=StarTV_51859&SecretKey=NtvApiSecret2014*&.m3u8"
        },
        {
            "season": 1,
            "episode": 41,
            "name": "41. Bölüm",
            "overview": "",
            "still_path": "https://media.startv.com.tr/star-tv/images/62dcc3ab4920b22d0abeecdd.jpg",
            "vote_average": 0.0,
            "link": "https://dygvideo.dygdigital.com/api/redirect?PublisherId=1&ReferenceId=StarTV_51992&SecretKey=NtvApiSecret2014*&.m3u8"
        },
        {
            "season": 1,
            "episode": 42,
            "name": "42. Bölüm",
            "overview": "",
            "still_path": "https://media.startv.com.tr/star-tv/images/72bfe2e742f2b47cd8e86699.jpg",
            "vote_average": 0.0,
            "link": "https://dygvideo.dygdigital.com/api/redirect?PublisherId=1&ReferenceId=StarTV_52140&SecretKey=NtvApiSecret2014*&.m3u8"
        },
        {
            "season": 1,
            "episode": 43,
            "name": "43. Bölüm",
            "overview": "",
            "still_path": "https://media.startv.com.tr/star-tv/images/755dd9134f3a88159b73e9ec.jpg",
            "vote_average": 0.0,
            "link": "https://dygvideo.dygdigital.com/api/redirect?PublisherId=1&ReferenceId=StarTV_52255&SecretKey=NtvApiSecret2014*&.m3u8"
        },
        {
            "season": 1,
            "episode": 44,
            "name": "44. Bölüm",
            "overview": "",
            "still_path": "https://media.startv.com.tr/star-tv/images/406da1054246a838b27509d6.jpg",
            "vote_average": 0.0,
            "link": "https://dygvideo.dygdigital.com/api/redirect?PublisherId=1&ReferenceId=StarTV_52506&SecretKey=NtvApiSecret2014*&.m3u8"
        },
        {
            "season": 1,
            "episode": 45,
            "name": "45. Bölüm",
            "overview": "",
            "still_path": "https://media.startv.com.tr/star-tv/images/f419bc814b0ba763fa893968.jpg",
            "vote_average": 0.0,
            "link": "https://dygvideo.dygdigital.com/api/redirect?PublisherId=1&ReferenceId=StarTV_52652&SecretKey=NtvApiSecret2014*&.m3u8"
        },
        {
            "season": 1,
            "episode": 46,
            "name": "46. Bölüm",
            "overview": "",
            "still_path": "https://media.startv.com.tr/star-tv/images/02cff92345d79b864eb336fb.jpg",
            "vote_average": 0.0,
            "link": "https://dygvideo.dygdigital.com/api/redirect?PublisherId=1&ReferenceId=StarTV_52776&SecretKey=NtvApiSecret2014*&.m3u8"
        },
        {
            "season": 1,
            "episode": 47,
            "name": "47. Bölüm",
            "overview": "",
            "still_path": "https://media.startv.com.tr/star-tv/images/ac32cea84db08efa17952fb4.jpg",
            "vote_average": 0.0,
            "link": "https://dygvideo.dygdigital.com/api/redirect?PublisherId=1&ReferenceId=StarTV_52915&SecretKey=NtvApiSecret2014*&.m3u8"
        },
        {
            "season": 1,
            "episode": 48,
            "name": "48. Bölüm",
            "overview": "",
            "still_path": "https://media.startv.com.tr/star-tv/images/956d0e4b4b1ba680e5bb23a4.jpg",
            "vote_average": 0.0,
            "link": "https://dygvideo.dygdigital.com/api/redirect?PublisherId=1&ReferenceId=StarTV_53237&SecretKey=NtvApiSecret2014*&.m3u8"
        },
        {
            "season": 1,
            "episode": 49,
            "name": "49. Bölüm",
            "overview": "",
            "still_path": "https://media.startv.com.tr/star-tv/images/288279cf44b08b5e4d6c7d71.jpg",
            "vote_average": 0.0,
            "link": "https://dygvideo.dygdigital.com/api/redirect?PublisherId=1&ReferenceId=StarTV_53357&SecretKey=NtvApiSecret2014*&.m3u8"
        },
        {
            "season": 1,
            "episode": 50,
            "name": "50. Bölüm",
            "overview": "",
            "still_path": "https://media.startv.com.tr/star-tv/images/da26545d43ffabf97f328e32.jpg",
            "vote_average": 0.0,
            "link": "https://dygvideo.dygdigital.com/api/redirect?PublisherId=1&ReferenceId=StarTV_53593&SecretKey=NtvApiSecret2014*&.m3u8"
        },
        {
            "season": 1,
            "episode": 51,
            "name": "51. Bölüm",
            "overview": "",
            "still_path": "https://media.startv.com.tr/star-tv/images/520043074489a695a3171a83.jpg",
            "vote_average": 0.0,
            "link": "https://dygvideo.dygdigital.com/api/redirect?PublisherId=1&ReferenceId=StarTV_53715&SecretKey=NtvApiSecret2014*&.m3u8"
        },
        {
            "season": 1,
            "episode": 52,
            "name": "52. Bölüm",
            "overview": "",
            "still_path": "https://media.startv.com.tr/star-tv/images/449f61e148349607d3b8a38c.jpg",
            "vote_average": 0.0,
            "link": "https://dygvideo.dygdigital.com/api/redirect?PublisherId=1&ReferenceId=StarTV_53855&SecretKey=NtvApiSecret2014*&.m3u8"
        }
    ],
    "update_date": "2026-03-11 06:39:24"
}