{
    "id": 256624,
    "imdb_id": "tt32596156",
    "name": "Talamasca Gizli Düzen",
    "poster": "https://image.tmdb.org/t/p/w500/qmmHl3EiFKuDLTVYHGwlV9UhtNw.jpg",
    "year": "2025",
    "genres": [
        "Bilim Kurgu & Fantazi"
    ],
    "cast": [
        "Nicholas Denton",
        "Celine Buckens",
        "Maisie Richardson-Sellers",
        "William Fichtner",
        "Elizabeth McGovern"
    ],
    "episodes": [
        {
            "season": 1,
            "episode": 1,
            "link": "https://vidmody.com/vs/tt32596156/s1/e01"
        }
    ]
}