{
    "id": 119051,
    "imdb_id": "tt13443470",
    "name": "Wednesday",
    "poster": "https://image.tmdb.org/t/p/w500/36xXlhEpQqVVPuiZhfoQuaY4OlA.jpg",
    "year": "2022",
    "genres": [
        "Bilim Kurgu & Fantazi",
        "Gizem",
        "Komedi"
    ],
    "cast": [
        "Jenna Ortega",
        "Steve Buscemi",
        "Emma Myers",
        "Hunter Doohan",
        "Joy Sunday"
    ],
    "episodes": [
        {
            "season": 1,
            "episode": 1,
            "link": "https://vidmody.com/vs/tt13443470/s1/e01"
        }
    ]
}